aplpy/__init__.py
aplpy/axis_labels.py
aplpy/colorbar.py
aplpy/compat.py
aplpy/conftest.py
aplpy/convolve_util.py
aplpy/core.py
aplpy/decorators.py
aplpy/frame.py
aplpy/grid.py
aplpy/header.py
aplpy/layers.py
aplpy/overlays.py
aplpy/regions.py
aplpy/rgb.py
aplpy/slicer.py
aplpy/tick_labels.py
aplpy/ticks.py
aplpy/version.py
aplpy/tests/__init__.py
aplpy/tests/helpers.py
aplpy/tests/setup_package.py
aplpy/tests/test_axis_labels.py
aplpy/tests/test_beam.py
aplpy/tests/test_colorbar.py
aplpy/tests/test_contour.py
aplpy/tests/test_convolve.py
aplpy/tests/test_downsample.py
aplpy/tests/test_frame.py
aplpy/tests/test_grid.py
aplpy/tests/test_images.py
aplpy/tests/test_init_cube.py
aplpy/tests/test_init_image.py
aplpy/tests/test_layers.py
aplpy/tests/test_misc.py
aplpy/tests/test_pixworldmarkers.py
aplpy/tests/test_rgb.py
aplpy/tests/test_save.py
aplpy/tests/test_scalebar.py
aplpy/tests/test_subplot.py
aplpy/tests/test_tick_labels.py
aplpy/tests/test_ticks.py
aplpy/tests/test_vectors.py
aplpy/tests/data/__init__.py
aplpy/tests/data/shapes.reg
aplpy/tests/data/2d_fits/1904-66_AIR.hdr
aplpy/tests/data/2d_fits/1904-66_AIT.hdr
aplpy/tests/data/2d_fits/1904-66_ARC.hdr
aplpy/tests/data/2d_fits/1904-66_AZP.hdr
aplpy/tests/data/2d_fits/1904-66_BON.hdr
aplpy/tests/data/2d_fits/1904-66_CAR.hdr
aplpy/tests/data/2d_fits/1904-66_CEA.hdr
aplpy/tests/data/2d_fits/1904-66_COD.hdr
aplpy/tests/data/2d_fits/1904-66_COE.hdr
aplpy/tests/data/2d_fits/1904-66_COO.hdr
aplpy/tests/data/2d_fits/1904-66_COP.hdr
aplpy/tests/data/2d_fits/1904-66_CSC.hdr
aplpy/tests/data/2d_fits/1904-66_CYP.hdr
aplpy/tests/data/2d_fits/1904-66_HPX.hdr
aplpy/tests/data/2d_fits/1904-66_MER.hdr
aplpy/tests/data/2d_fits/1904-66_MOL.hdr
aplpy/tests/data/2d_fits/1904-66_NCP.hdr
aplpy/tests/data/2d_fits/1904-66_PAR.hdr
aplpy/tests/data/2d_fits/1904-66_PCO.hdr
aplpy/tests/data/2d_fits/1904-66_QSC.hdr
aplpy/tests/data/2d_fits/1904-66_SFL.hdr
aplpy/tests/data/2d_fits/1904-66_SIN.hdr
aplpy/tests/data/2d_fits/1904-66_STG.hdr
APLpy-2.2.0.dist-info/LICENSE.md
APLpy-2.2.0.dist-info/METADATA
APLpy-2.2.0.dist-info/WHEEL
APLpy-2.2.0.dist-info/top_level.txt
APLpy-2.2.0.dist-info/RECORD
