Metadata-Version: 2.1
Name: APLpy
Version: 2.2.0
Summary: The Astronomical Plotting Library in Python
Author-email: Thomas Robitaille and Eli Bressert <thomas.robitaille@gmail.com>
License: MIT
Project-URL: Homepage, http://aplpy.github.io
Requires-Python: >=3.10
License-File: LICENSE.md
Requires-Dist: numpy >=1.22
Requires-Dist: astropy >=5.0
Requires-Dist: matplotlib >=3.5
Requires-Dist: reproject >=0.9
Requires-Dist: pyregion >=2.2
Requires-Dist: pillow >=9.0
Requires-Dist: pyavm >=0.9.6
Requires-Dist: scikit-image >=0.20
Requires-Dist: shapely >=2.0
Provides-Extra: docs
Requires-Dist: sphinx-astropy ; extra == 'docs'
Provides-Extra: test
Requires-Dist: pytest-astropy ; extra == 'test'
Requires-Dist: pytest-mpl ; extra == 'test'
